chunnel/__init__.py
chunnel/channel.py
chunnel/main.py
chunnel/messages.py
chunnel/socket.py
chunnel/utils.py
chunnel/transports/__init__.py
chunnel/transports/base.py
chunnel/transports/websocket.py
chunnel-0.1.0.dist-info/DESCRIPTION.rst
chunnel-0.1.0.dist-info/METADATA
chunnel-0.1.0.dist-info/metadata.json
chunnel-0.1.0.dist-info/RECORD
chunnel-0.1.0.dist-info/top_level.txt
chunnel-0.1.0.dist-info/WHEEL
test/__init__.py
test/conftest.py
test/shared.py
test/test_against_phoenix.py
test/test_channel.py
test/test_socket.py
test/test_utils.py
